extendingPython/__init__.py
extendingPython/GiteeAPI/Activity.py
extendingPython/GiteeAPI/Exceptions.py
extendingPython/GiteeAPI/__init__.py
extendingPython/SQLs/MySQL.py
extendingPython/SQLs/__init__.py
extendingPython/cloudflareDDNS/__init__.py
extendingPython/cloudflareDDNS/cfddns.py
extendingPython/getYourIP/__init__.py
extendingPython/getYourIP/getIP.py
extendingPython-0.0.2.dist-info/LICENSE
extendingPython-0.0.2.dist-info/METADATA
extendingPython-0.0.2.dist-info/WHEEL
extendingPython-0.0.2.dist-info/top_level.txt
extendingPython-0.0.2.dist-info/RECORD
